LICENSE
README.md
setup.py
ecml_tools/__init__.py
ecml_tools/__main__.py
ecml_tools/grids.py
ecml_tools/provenance.py
ecml_tools.egg-info/PKG-INFO
ecml_tools.egg-info/SOURCES.txt
ecml_tools.egg-info/dependency_links.txt
ecml_tools.egg-info/entry_points.txt
ecml_tools.egg-info/requires.txt
ecml_tools.egg-info/top_level.txt
ecml_tools.egg-info/zip-safe
ecml_tools/commands/__init__.py
ecml_tools/commands/compare.py
ecml_tools/commands/copy.py
ecml_tools/commands/create.py
ecml_tools/commands/scan.py
ecml_tools/commands/inspect/__init__.py
ecml_tools/commands/inspect/zarr.py
ecml_tools/create/__init__.py
ecml_tools/create/check.py
ecml_tools/create/config.py
ecml_tools/create/input.py
ecml_tools/create/loaders.py
ecml_tools/create/patch.py
ecml_tools/create/statistics.py
ecml_tools/create/template.py
ecml_tools/create/utils.py
ecml_tools/create/writer.py
ecml_tools/create/zarr.py
ecml_tools/create/functions/__init__.py
ecml_tools/create/functions/actions/__init__.py
ecml_tools/create/functions/actions/accumulations.py
ecml_tools/create/functions/actions/constants.py
ecml_tools/create/functions/actions/empty.py
ecml_tools/create/functions/actions/ensemble_perturbations.py
ecml_tools/create/functions/actions/grib.py
ecml_tools/create/functions/actions/mars.py
ecml_tools/create/functions/actions/netcdf.py
ecml_tools/create/functions/actions/opendap.py
ecml_tools/create/functions/actions/source.py
ecml_tools/create/functions/actions/tendencies.py
ecml_tools/create/functions/steps/__init__.py
ecml_tools/create/functions/steps/empty.py
ecml_tools/create/functions/steps/noop.py
ecml_tools/create/functions/steps/rename.py
ecml_tools/create/functions/steps/rotate_winds.py
ecml_tools/create/functions/steps/unrotate_winds.py
ecml_tools/data/__init__.py
ecml_tools/data/concat.py
ecml_tools/data/dataset.py
ecml_tools/data/debug.py
ecml_tools/data/ensemble.py
ecml_tools/data/forewards.py
ecml_tools/data/grids.py
ecml_tools/data/indexing.py
ecml_tools/data/join.py
ecml_tools/data/masked.py
ecml_tools/data/misc.py
ecml_tools/data/select.py
ecml_tools/data/statistics.py
ecml_tools/data/stores.py
ecml_tools/data/subset.py
ecml_tools/utils/__init__.py
ecml_tools/utils/humanize.py
ecml_tools/utils/text.py
