Metadata-Version: 2.1
Name: ecml-tools
Version: 0.6.1
Summary: A package to hold various functions to support training of ML models on ECMWF data.
Home-page: https://github.com/ecmwf-lab/ecml-tools
Author: European Centre for Medium-Range Weather Forecasts (ECMWF)
Author-email: software.support@ecmwf.int
License: Apache License Version 2.0
Keywords: tool
Classifier: Development Status :: 3 - Alpha
Classifier: Intended Audience :: Developers
Classifier: License :: OSI Approved :: Apache Software License
Classifier: Programming Language :: Python :: 3
Classifier: Programming Language :: Python :: 3.9
Classifier: Programming Language :: Python :: 3.10
Classifier: Programming Language :: Python :: 3.11
Classifier: Programming Language :: Python :: Implementation :: CPython
Classifier: Programming Language :: Python :: Implementation :: PyPy
Classifier: Operating System :: OS Independent
Provides-Extra: data
Provides-Extra: remote
Provides-Extra: provenance
Provides-Extra: create
Provides-Extra: all
License-File: LICENSE
